pandas_excel_limitedrows/__init__.py
pandas_excel_limitedrows/main.py
pandas_excel_limitedrows/engines/__init__.py
pandas_excel_limitedrows/engines/_openpyxl.py
pandas_excel_limitedrows/engines/_pyxlsb.py
pandas_excel_limitedrows/engines/_xlrd.py
pandas_excel_limitedrows-2.0.1.dist-info/LICENSE
pandas_excel_limitedrows-2.0.1.dist-info/METADATA
pandas_excel_limitedrows-2.0.1.dist-info/WHEEL
pandas_excel_limitedrows-2.0.1.dist-info/top_level.txt
pandas_excel_limitedrows-2.0.1.dist-info/RECORD
