Metadata-Version: 2.1
Name: pandas-excel-limitedrows
Version: 2.0.1
Summary: Pandas Extension Package used to read Excel files with limit rows
Home-page: https://github.com/ibolorino/pandas-excel-limitedrows
Author: Ivan Bolorino
Author-email: ivan.bolorino@gmail.com
License: MIT
Keywords: dev,web,pandas,excel,data science
Platform: UNKNOWN
Classifier: Intended Audience :: Developers
Classifier: License :: OSI Approved :: MIT License
Classifier: Natural Language :: English
Classifier: Programming Language :: Python :: 3
Requires-Dist: openpyxl
Requires-Dist: pandas
Requires-Dist: pyxlsb
Requires-Dist: xlrd
